PortableTab/__init__.py
PortableTab/__main__.py
PortableTab/base_table.py
PortableTab/capnp_manager.py
PortableTab/capnp_table.py
PortableTab/exceptions.py
portabletab-0.3.7.post1.dist-info/LICENSE
portabletab-0.3.7.post1.dist-info/METADATA
portabletab-0.3.7.post1.dist-info/WHEEL
portabletab-0.3.7.post1.dist-info/entry_points.txt
portabletab-0.3.7.post1.dist-info/RECORD
