Metadata-Version: 2.1
Name: PortableTab
Version: 0.3.7.post1
Summary: Python package for serializing tables in portable format with Capnp.
License: MIT
Author: Takeshi Sagara
Author-email: sagara@info-proto.com
Requires-Python: >=3.9,<3.13
Classifier: License :: OSI Approved :: MIT License
Classifier: Programming Language :: Python :: 3
Classifier: Programming Language :: Python :: 3.9
Classifier: Programming Language :: Python :: 3.10
Classifier: Programming Language :: Python :: 3.11
Classifier: Programming Language :: Python :: 3.12
Requires-Dist: docopt-ng (>=0.6.2,<0.7.0)
Requires-Dist: marisa-trie (>=1.1.0)
Requires-Dist: pycapnp (>=2.0.0,<3.0.0)
Requires-Dist: zipp (>=3.19.1)
